[
    {
        "type": "TEXT",
        "id": "text_0",
        "position": {
            "x": 0,
            "y": 0,
            "width": 328
        },
        "text": "asdasd"
    },
    {
        "type": "TEXT_FIELD",
        "id": "text_field_2",
        "position": {
            "x": 0,
            "y": 0,
            "width": 328,
            "height": 56
        },
        "hint": "İpucu metni",
        "label": "Etiket"
    },
    {
        "type": "CHECKBOX",
        "id": "checkbox_3",
        "position": {
            "x": 0,
            "y": 0,
            "width": 160
        },
        "label": "Onay Kutusu",
        "isChecked": true
    },
    {
        "type": "RADIO_BUTTON",
        "id": "radio_button_4",
        "position": {
            "x": 0,
            "y": 0,
            "width": 160
        },
        "label": "Seçenek",
        "group": "grup1"
    },
    {
        "type": "TEXT",
        "id": "text_0",
        "position": {
            "x": 0,
            "y": 0,
            "width": 328
        },
        "text": "asdasd"
    },
    {
        "type": "TEXT_FIELD",
        "id": "text_field_1",
        "position": {
            "x": 0,
            "y": 0,
            "width": 328,
            "height": 56
        },
        "hint": "asdasda",
        "label": "Etiket"
    },
    {
        "type": "TEXT_FIELD",
        "id": "text_field_2",
        "position": {
            "x": 0,
            "y": 0,
            "width": 328,
            "height": 56
        },
        "hint": "İpucu metni",
        "label": "Etiket"
    }
]